eveuniverse/__init__.py
eveuniverse/admin.py
eveuniverse/app_settings.py
eveuniverse/apps.py
eveuniverse/backends.py
eveuniverse/constants.py
eveuniverse/helpers.py
eveuniverse/providers.py
eveuniverse/tasks.py
eveuniverse/utils.py
eveuniverse/core/__init__.py
eveuniverse/core/dotlan.py
eveuniverse/core/esitools.py
eveuniverse/core/eveimageserver.py
eveuniverse/core/eveitems.py
eveuniverse/core/evemicros.py
eveuniverse/core/evesdeapi.py
eveuniverse/core/eveskinserver.py
eveuniverse/core/evewho.py
eveuniverse/core/evexml.py
eveuniverse/core/zkillboard.py
eveuniverse/management/commands/__init__.py
eveuniverse/management/commands/eveuniverse_fix_section_flags.py
eveuniverse/management/commands/eveuniverse_load_data.py
eveuniverse/management/commands/eveuniverse_load_types.py
eveuniverse/management/commands/eveuniverse_purge_data.py
eveuniverse/managers/__init__.py
eveuniverse/managers/entities.py
eveuniverse/managers/sde.py
eveuniverse/managers/universe.py
eveuniverse/migrations/0001_initial.py
eveuniverse/migrations/0002_load_eveunit.py
eveuniverse/migrations/0003_evemarketprice.py
eveuniverse/migrations/0004_effect_longer_name.py
eveuniverse/migrations/0005_type_materials_and_sections.py
eveuniverse/migrations/0006_alter_evedogmaeffectmodifier_operator.py
eveuniverse/migrations/0007_evetype_description.py
eveuniverse/migrations/0008_eveindustryactivity_alter_evetype_enabled_sections_and_more.py
eveuniverse/migrations/0009_load_industry_activities.py
eveuniverse/migrations/0010_alter_eveindustryactivityduration_eve_type_and_more.py
eveuniverse/migrations/0011_extend_industry_activites.py
eveuniverse/migrations/__init__.py
eveuniverse/migrations/eve_unit.json
eveuniverse/migrations/industry_activities.json
eveuniverse/models/__init__.py
eveuniverse/models/base.py
eveuniverse/models/entities.py
eveuniverse/models/sde.py
eveuniverse/models/universe_1.py
eveuniverse/models/universe_2.py
eveuniverse/static/eveuniverse/skin_generic_128.png
django_eveuniverse-1.6.0.dist-info/licenses/LICENSE
django_eveuniverse-1.6.0.dist-info/WHEEL
django_eveuniverse-1.6.0.dist-info/METADATA
django_eveuniverse-1.6.0.dist-info/RECORD
