Metadata-Version: 2.4
Name: django-eveuniverse
Version: 1.6.0
Summary: Complete set of Eve Universe models with on-demand loading from ESI.
Author-email: Erik Kalkoken <kalkoken87@gmail.com>
Requires-Python: >=3.8
Classifier: Environment :: Web Environment
Classifier: Framework :: Django
Classifier: Framework :: Django :: 3.2
Classifier: Framework :: Django :: 4.2
Classifier: Intended Audience :: Developers
Classifier: License :: OSI Approved :: MIT License
Classifier: Operating System :: OS Independent
Classifier: Programming Language :: Python
Classifier: Programming Language :: Python :: 3.8
Classifier: Programming Language :: Python :: 3.9
Classifier: Programming Language :: Python :: 3.10
Classifier: Programming Language :: Python :: 3.11
Classifier: Programming Language :: Python :: 3.12
Classifier: Topic :: Internet :: WWW/HTTP
Classifier: Topic :: Internet :: WWW/HTTP :: Dynamic Content
License-File: LICENSE
Requires-Dist: celery>=4.0.2
Requires-Dist: celery_once>=3.0.1
Requires-Dist: django-bitfield>=2.2
Requires-Dist: django-esi>=4
Requires-Dist: django>=3.2
Requires-Dist: requests
Project-URL: Documentation, https://django-eveuniverse.readthedocs.io/en/latest/
Project-URL: Source, https://gitlab.com/ErikKalkoken/django-eveuniverse
Project-URL: Tracker, https://gitlab.com/ErikKalkoken/django-eveuniverse/issues
